atsphinx/goto_top/__init__.py
atsphinx/goto_top/locales/ja/LC_MESSAGES/atsphinx.goto_top.mo
atsphinx/goto_top/locales/ja/LC_MESSAGES/atsphinx.goto_top.po
atsphinx/goto_top/static/goto-top/arrow-up-to-line.svg
atsphinx/goto_top/static/goto-top/main.js_t
atsphinx/goto_top/static/goto-top/style.css_t
atsphinx/goto_top/templates/goto-top/navigation-image.html
atsphinx/goto_top/templates/goto-top/navigation-text.html
atsphinx/goto_top/templates/goto-top/navigation.html
atsphinx_goto_top-0.2.0.dist-info/METADATA
atsphinx_goto_top-0.2.0.dist-info/WHEEL
atsphinx_goto_top-0.2.0.dist-info/licenses/LICENSE
atsphinx_goto_top-0.2.0.dist-info/RECORD
